[
  {
    "line_userid": "dr.test.id",
    "information": null,
    "permission": "doctor",
    "password": "dr.test.pass",
    "name": "TestDoctor"
  },
  {
    "line_userid": "pt.test.id",
    "information": null,
    "permission": "patient",
    "password": null,
    "name": "TestPatient",
    "birth_date": "0916",
    "id_number": "T123",
    "phone": "test",
    "blood_type": null,
    "emergency_contact": null,
    "emergency_contact_phone": null,
    "email": null,
    "height": null,
    "weight": null,
    "medical_history": null,
    "notes": null
  },
  {
    "line_userid": "Ufc4c95ce42186b6965c5f684fa38c1a1",
    "information": null,
    "permission": "patient",
    "password": null,
    "name": "FishYu",
    "birth_date": "1001",
    "id_number": "A13301124",
    "phone": "0987331763",
    "blood_type": "B",
    "emergency_contact": "CH",
    "emergency_contact_phone": "0966534812",
    "email": "sun@gmail.com",
    "height": "165",
    "weight": "60",
    "medical_history": "Height problem",
    "notes": null
  }
]